llm_usage_tracker/__init__.py
llm_usage_tracker/crew_helpers.py
llm_usage_tracker/decorators.py
llm_usage_tracker/pricing.py
llm_usage_tracker/tool_logging.py
llm_usage_tracker/trace_log.py
llm_usage_tracker/tracker.py
llm_usage_tracker/version.py
llm_usage_tracker-0.1.1.dist-info/licenses/LICENSE
llm_usage_tracker-0.1.1.dist-info/METADATA
llm_usage_tracker-0.1.1.dist-info/WHEEL
llm_usage_tracker-0.1.1.dist-info/top_level.txt
llm_usage_tracker-0.1.1.dist-info/RECORD
