Metadata-Version: 2.4
Name: llm-usage-tracker
Version: 0.1.1
Summary: Drop-in token + cost tracker for OpenAI / LiteLLM / Gemini with caching awareness
Author-email: Gobi <gobivellingiri@gmail.com>
License: MIT
Keywords: llm,openai,token-tracking,cost-tracking,litellm,gemini
Classifier: Development Status :: 4 - Beta
Classifier: Intended Audience :: Developers
Classifier: License :: OSI Approved :: MIT License
Classifier: Programming Language :: Python :: 3
Classifier: Programming Language :: Python :: 3.9
Classifier: Programming Language :: Python :: 3.10
Classifier: Programming Language :: Python :: 3.11
Classifier: Programming Language :: Python :: 3.12
Requires-Python: >=3.9
License-File: LICENSE
Provides-Extra: litellm
Requires-Dist: litellm>=1.42.0; extra == "litellm"
Provides-Extra: gemini
Requires-Dist: google-generativeai>=0.7.2; extra == "gemini"
Provides-Extra: all
Requires-Dist: litellm>=1.42.0; extra == "all"
Requires-Dist: google-generativeai>=0.7.2; extra == "all"
Dynamic: license-file
